linkfixer/__init__.py
linkfixer/linkfixer.py
linkfixer-0.2.1.dist-info/LICENSE
linkfixer-0.2.1.dist-info/METADATA
linkfixer-0.2.1.dist-info/WHEEL
linkfixer-0.2.1.dist-info/top_level.txt
linkfixer-0.2.1.dist-info/RECORD
