Metadata-Version: 2.1
Name: linkfixer
Version: 0.2.1
Summary: A Python library to normalize, clean, and validate URLs.
Author: Renukumar R
Author-email: renu2babu1110@gmail.com
License: MIT
Classifier: Programming Language :: Python :: 3
Classifier: License :: OSI Approved :: MIT License
Classifier: Operating System :: OS Independent
Classifier: Topic :: Internet :: WWW/HTTP :: Site Management
Classifier: Topic :: Software Development :: Libraries :: Python Modules
Requires-Python: >=3.7
License-File: LICENSE
Requires-Dist: idna>=2.5
